stackzilla/attribute/__init__.py
stackzilla/attribute/attribute.py
stackzilla/blueprint/__init__.py
stackzilla/blueprint/blueprint.py
stackzilla/blueprint/exceptions.py
stackzilla/cli/__init__.py
stackzilla/cli/_callbacks.py
stackzilla/cli/blueprint.py
stackzilla/cli/compute.py
stackzilla/cli/database.py
stackzilla/cli/kubernetes.py
stackzilla/cli/main.py
stackzilla/cli/metadata.py
stackzilla/cli/options.py
stackzilla/cli/resource.py
stackzilla/cli/utils.py
stackzilla/database/__init__.py
stackzilla/database/base.py
stackzilla/database/exceptions.py
stackzilla/database/sqlite.py
stackzilla/diff/__init__.py
stackzilla/diff/diff.py
stackzilla/diff/exceptions.py
stackzilla/events/__init__.py
stackzilla/events/events.py
stackzilla/events/exceptions.py
stackzilla/graph/__init__.py
stackzilla/graph/exceptions.py
stackzilla/graph/graph.py
stackzilla/graph/test_graph_basic.py
stackzilla/host_services/__init__.py
stackzilla/host_services/exceptions.py
stackzilla/host_services/groups.py
stackzilla/host_services/host_services.py
stackzilla/host_services/users.py
stackzilla/importer/__init__.py
stackzilla/importer/base.py
stackzilla/importer/db_importer.py
stackzilla/importer/exceptions.py
stackzilla/importer/importer.py
stackzilla/logger/__init__.py
stackzilla/logger/base.py
stackzilla/logger/core.py
stackzilla/logger/provider.py
stackzilla/logger/utils.py
stackzilla/provider/null/__init__.py
stackzilla/provider/null/base.py
stackzilla/provider/null/instance.py
stackzilla/provider/null/load_balancer.py
stackzilla/provider/null/volume.py
stackzilla/resource/__init__.py
stackzilla/resource/base.py
stackzilla/resource/exceptions.py
stackzilla/resource/kubernetes.py
stackzilla/resource/ssh_key.py
stackzilla/resource/compute/__init__.py
stackzilla/resource/compute/compute.py
stackzilla/resource/compute/exceptions.py
stackzilla/utils/__init__.py
stackzilla/utils/constants.py
stackzilla/utils/numbers.py
stackzilla/utils/ssh.py
stackzilla/utils/string.py
stackzilla-0.2.1.dist-info/LICENSE
stackzilla-0.2.1.dist-info/METADATA
stackzilla-0.2.1.dist-info/WHEEL
stackzilla-0.2.1.dist-info/entry_points.txt
stackzilla-0.2.1.dist-info/top_level.txt
stackzilla-0.2.1.dist-info/RECORD
