Metadata-Version: 2.1
Name: stackzilla
Version: 0.2.1
Summary: An ORM for your application stack.
Home-page: https://github.com/Stackzilla/stackzilla
Author: Zimventures, LLC
Author-email: rob@stackzilla.dev
License: GNU Affero General Public License v3
Platform: any
Classifier: Development Status :: 3 - Alpha
Classifier: Environment :: Console
Classifier: Intended Audience :: Developers
Classifier: License :: OSI Approved :: GNU Affero General Public License v3
Classifier: Operating System :: POSIX
Classifier: Programming Language :: Python :: 3
Classifier: Programming Language :: Python :: 3.7
Classifier: Programming Language :: Python :: 3.8
Classifier: Programming Language :: Python :: 3.9
Classifier: Topic :: Software Development :: Libraries
Requires-Python: >3.6
License-File: LICENSE
Requires-Dist: click (==8.1.3)
Requires-Dist: colorama (==0.4.5)
Requires-Dist: cryptography (==38.0.1)
Requires-Dist: parallel-ssh (==2.12.0)
Requires-Dist: prettytable (==3.5.0)
Provides-Extra: dev
Requires-Dist: invoke (==1.7.1) ; extra == 'dev'
Requires-Dist: wheel ; extra == 'dev'
Provides-Extra: test
Requires-Dist: coverage (==6.5.0) ; extra == 'test'
Requires-Dist: invoke (==1.7.1) ; extra == 'test'
Requires-Dist: isort (==5.10.1) ; extra == 'test'
Requires-Dist: mypy (==0.971) ; extra == 'test'
Requires-Dist: mypy-extensions (==0.4.3) ; extra == 'test'
Requires-Dist: pydocstyle (==6.1.1) ; extra == 'test'
Requires-Dist: pyflakes (==2.5.0) ; extra == 'test'
Requires-Dist: pylint ; extra == 'test'
Requires-Dist: pytest ; extra == 'test'
Requires-Dist: pytest-cov ; extra == 'test'
